setup.py
TestAnalyzer/__init__.py
team_city_test_analyzer.egg-info/PKG-INFO
team_city_test_analyzer.egg-info/SOURCES.txt
team_city_test_analyzer.egg-info/dependency_links.txt
team_city_test_analyzer.egg-info/not-zip-safe
team_city_test_analyzer.egg-info/top_level.txt