Metadata-Version: 1.0
Name: team-city-test-analyzer
Version: 1.0
Summary: For use with .csv ouput files from TeamCity
Home-page: http://elevenwireless.com
Author: Joe Good
Author-email: jgood@elevenwireless.com
License: MIT
Platform: UNKNOWN
